deepex/DeepEX.py
deepex/__init__.py
deepex/model/__init__.py
deepex/model/deepfm.py
deepex-0.0.17.dist-info/METADATA
deepex-0.0.17.dist-info/WHEEL
deepex-0.0.17.dist-info/top_level.txt
deepex-0.0.17.dist-info/RECORD
